cli/__init__.py
cli/cli.py
uma_auth_cli-0.2.1.dist-info/LICENSE
uma_auth_cli-0.2.1.dist-info/METADATA
uma_auth_cli-0.2.1.dist-info/WHEEL
uma_auth_cli-0.2.1.dist-info/entry_points.txt
uma_auth_cli-0.2.1.dist-info/top_level.txt
uma_auth_cli-0.2.1.dist-info/RECORD
