Metadata-Version: 2.1
Name: uma-auth-cli
Version: 0.2.1
Summary: UMA Auth CLI tool for Client Apps.
Home-page: https://docs.uma.me/
Author: Lightspark Group, Inc.
Author-email: info@lightspark.com
License: Apache-2.0
Project-URL: Documentation, https://github.com/uma-universal-money-address/uma-auth-cli/blob/main/README.md
Project-URL: Source Code, https://github.com/uma-universal-money-address/uma-auth-cli
License-File: LICENSE
Requires-Dist: typer
Requires-Dist: nostr-sdk
